sotoki/__about__.py
sotoki/__init__.py
sotoki/__main__.py
sotoki/archives.py
sotoki/constants.py
sotoki/context.py
sotoki/css.py
sotoki/entrypoint.py
sotoki/illustration.png
sotoki/logging.py
sotoki/models.py
sotoki/posts.py
sotoki/renderer.py
sotoki/scraper.py
sotoki/tags.py
sotoki/users.py
sotoki/templates/about.html
sotoki/templates/base.html
sotoki/templates/linked_list.html
sotoki/templates/pagination.html
sotoki/templates/post_layout.html
sotoki/templates/question.html
sotoki/templates/question_list_item.html
sotoki/templates/questions.html
sotoki/templates/single_comment.html
sotoki/templates/tag.html
sotoki/templates/tags.html
sotoki/templates/user.html
sotoki/templates/user_card.html
sotoki/templates/users.html
sotoki/utils/__init__.py
sotoki/utils/exceptions.py
sotoki/utils/executor.py
sotoki/utils/generator.py
sotoki/utils/html.py
sotoki/utils/imager.py
sotoki/utils/misc.py
sotoki/utils/paginator.py
sotoki/utils/preparation.py
sotoki/utils/progress.py
sotoki/utils/s3.py
sotoki/utils/sevenzip.py
sotoki/utils/shared.py
sotoki/utils/database/files.py
sotoki/utils/database/posts.py
sotoki/utils/database/redisdb.py
sotoki/utils/database/tags.py
sotoki/utils/database/users.py
sotoki-3.0.2.dist-info/METADATA
sotoki-3.0.2.dist-info/WHEEL
sotoki-3.0.2.dist-info/entry_points.txt
sotoki-3.0.2.dist-info/licenses/LICENSE
sotoki-3.0.2.dist-info/RECORD
