Metadata-Version: 2.4
Name: sotoki
Version: 3.0.2
Summary: Turn StackExchange dumps into ZIM files for offline usage
Project-URL: Donate, https://www.kiwix.org/en/support-us/
Project-URL: Homepage, https://github.com/openzim/sotoki
Author-email: openZIM <dev@openzim.org>
License: GPL-3.0-or-later
License-File: LICENSE
Keywords: offline,openzim,stackechange,stackoverflow,zim
Classifier: License :: OSI Approved :: GNU General Public License v3 or later (GPLv3+)
Classifier: Programming Language :: Python :: 3
Classifier: Programming Language :: Python :: 3.14
Requires-Python: <3.15,>=3.14
Requires-Dist: backoff==2.2.1
Requires-Dist: beautifulsoup4==4.14.2
Requires-Dist: bidict==0.23.1
Requires-Dist: cli-formatter==1.2.0
Requires-Dist: dependency-injector==4.48.2
Requires-Dist: jinja2-pluralize==0.3.0
Requires-Dist: jinja2==3.1.6
Requires-Dist: kiwixstorage==0.10.1
Requires-Dist: lxml==6.0.2
Requires-Dist: mistune==3.1.4
Requires-Dist: pif==0.8.2
Requires-Dist: psutil==7.1.3
Requires-Dist: py7zr==1.0.0
Requires-Dist: python-dateutil==2.9.0.post0
Requires-Dist: python-slugify==8.0.4
Requires-Dist: python-snappy==0.7.3
Requires-Dist: redis==7.1.0
Requires-Dist: tld==0.13.1
Requires-Dist: xml-to-dict==0.1.6
Requires-Dist: zimscraperlib==5.3.0
Provides-Extra: check
Requires-Dist: pyright==1.1.407; extra == 'check'
Provides-Extra: dev
Requires-Dist: black==25.11.0; extra == 'dev'
Requires-Dist: coverage==7.12.0; extra == 'dev'
Requires-Dist: debugpy==1.8.17; extra == 'dev'
Requires-Dist: invoke==2.2.1; extra == 'dev'
Requires-Dist: ipdb==0.13.13; extra == 'dev'
Requires-Dist: ipython==9.7.0; extra == 'dev'
Requires-Dist: pre-commit==4.5.0; extra == 'dev'
Requires-Dist: pyright==1.1.407; extra == 'dev'
Requires-Dist: pytest==9.0.1; extra == 'dev'
Requires-Dist: ruff==0.14.6; extra == 'dev'
Provides-Extra: lint
Requires-Dist: black==25.11.0; extra == 'lint'
Requires-Dist: ruff==0.14.6; extra == 'lint'
Provides-Extra: scripts
Requires-Dist: invoke==2.2.1; extra == 'scripts'
Provides-Extra: test
Requires-Dist: coverage==7.12.0; extra == 'test'
Requires-Dist: pytest==9.0.1; extra == 'test'
